{
    "探索生態島[都]在戶外活動嗎": [
        "戶外活動不僅有助於孩子的身心發展，也能增進對自然的認識和尊重。",
        "探索生態島提供孩子接觸自然環境的機會。",
        "是的，探索生態島主要是在戶外進行活動。",
        "孩子們可以在探索生態島中體驗戶外冒險和探索自然之美。",
        "探索生態島的活動注重體驗和互動，讓孩子從戶外環境中學習和成長。"
    ],
    "探索生態島在做什麼": [
        "探索生態島的活動規劃由引導員汪汪專業指導，帶領孩子們玩遊戲、創作和探索。",
        "進一步瞭解探索生態島的詳情，您可以參考官網上的相關資訊。",
        "探索生態島是一個讓孩子近距離接觸自然的活動。",
        "透過探索生態島，孩子們能夠培養對自然的熱愛和欣賞。",
        "在探索生態島中，孩子們可以在都市綠地中體驗自然的美好。"
    ],
    "探索生態島在幹嘛": [
        "這個計畫希望讓孩子透過自主探索，發現生活中更多可能性，並培養他們與自然環境的連結。",
        "透過引導員的帶領，孩子可以在綠地中遊戲、創作，並且學習對自然昆蟲的熱愛與尊重。",
        "探索生態島是為了讓孩子有機會接近自然，從都市中的綠地展開探險之旅。",
        "如果你對探索生態島感興趣，可以到官網https://pleyschool.org/camps/nature-bug/獲得更多詳細資訊喔！",
        "探索生態島的活動充滿趣味與互動，讓孩子在悠閒節奏下體驗自然的豐富之處。"
    ],
    "探索生態島的[特色]是什麼": [
        "透過生態島，孩子能夠在引導員的協助下，以自己的節奏探索自然，並進行遊戲與創作。",
        "生態島引導孩子愛護與熱愛自然環境，並透過與自然互動，啟發他們對生態保育的意識。",
        "探索生態島的特色在於注重孩子的自主性和與自然的連結，讓他們在遊戲中學習、成長和發現更多生活可能性。",
        "探索生態島獨特之處在於提供孩子近自然的機會，從都市中的綠地出發開展活動。",
        "在生態島，孩子可以接觸到豐富的自然素材，並透過這些素材的利用，培養他們的觀察力和創造力。"
    ],
    "探索生態島的[細節]": [
        "若對於探索生態島的細節有更多疑問，建議您參考官網提供的詳細資訊，那裡會有更多相關內容以供參考。",
        "在遊戲與創作的過程中，孩子們能夠按照自己的節奏，享受與大自然互動的樂趣。",
        "探索生態島是一個以都市綠地為起點的活動，讓孩子有機會接觸自然環境。",
        "在生態島中，有專業的引導員陪同孩子一同探索自然世界，特別是昆蟲。",
        "探索生態島不僅讓孩子體驗自然的美妙，還能培養他們對生命的尊重與保護的意識。"
    ],
    "探索生態島的[詳細][內容]": [
        "這個活動的目的是啟發孩子對自然的熱愛，並讓他們看到生活中更多豐富的可能性。",
        "探索生態島是一個讓孩子透過接觸自然，發現和探索當地生態的活動。",
        "在探索生態島中，孩子們透過與引導員一起遊戲和創作，以自己的節奏來體驗自然環境。",
        "探索生態島是一個富有教育意義又樂趣滿溢的活動，讓孩子們在大自然中學習和成長。",
        "孩子們會在綠地中參與各種有趣的活動，如採集植物、觀察昆蟲、與自然互動等，以提升他們的自然意識。"
    ],
    "有探索生態島的課表嗎": [
        "是的，我們為探索生態島設有課表，你可以在報名或詢問時索取。",
        "絕對！我們提供具體的探索生態島課表，讓您知道每天的活動安排和專案內容。",
        "是的，我們有探索生態島的課表，你可以在我們官方網站上檢視更多詳細訊息。",
        "是的，我們為探索生態島準備了一個清晰的課表，以確保每個參與者能夠充分體驗這個活動。",
        "當然！我們有為探索生態島制定了一份精心安排的課表。"
    ]
}